{
  "logo": {
    "href": "/",
    "src": "/gfx/svg/logo-2021.svg",
    "src2": "/gfx/svg/logo.svg",
    "title": "Home"
  },
  "menu": [{
    "href": "/articles/",
    "title": "My blog",
    "list": [{
      "href": "/side-projects/ui-dev-mentoring/reads/#newsletter",
      "title": "Newsletter❗"
    }]
  }, {
    "href": "/portfolio/",
    "title": "My portfolio",
    "list": [{
      "href": "/side-projects/",
      "title": "My projects"
    }]
  }, {
    "href": "/links/",
    "title": "My Links",
    "list": [{
      "href": "/favorites/",
      "title": "My Favorites"
    }]
  }, {
    "href": "/about/",
    "title": "About me",
    "list": [{
      "href": "/contact/",
      "title": "Contact me 📮"
    }]
  }]
}
